levenshtein_distance/__init__.py
levenshtein_distance/core.py
levenshtein_distance/shared_dcs.py
levenshtein_distance-1.0.1.dist-info/LICENSE
levenshtein_distance-1.0.1.dist-info/METADATA
levenshtein_distance-1.0.1.dist-info/WHEEL
levenshtein_distance-1.0.1.dist-info/top_level.txt
levenshtein_distance-1.0.1.dist-info/RECORD
